main.py
cashier_server-0.10.0.dist-info/METADATA
cashier_server-0.10.0.dist-info/WHEEL
cashier_server-0.10.0.dist-info/entry_points.txt
cashier_server-0.10.0.dist-info/licenses/LICENSE
cashier_server-0.10.0.dist-info/RECORD
