Metadata-Version: 2.4
Name: cashier-server
Version: 0.10.0
Summary: Cashier synchronization server in Python
License-File: LICENSE
Requires-Python: >=3.12
Requires-Dist: beancount>=3.1.0
Requires-Dist: beanquery>=0.2.0
Requires-Dist: fastapi>=0.115.12
Requires-Dist: loguru>=0.7.3
Requires-Dist: python-dotenv>=1.1.0
Requires-Dist: uvicorn>=0.34.2
